{
   "title": "А что с ними делать дальше? 1623703107.030645",
   "author": "Фостер Алан Дин",
   "img_path": "library\\images\\А что с ними делать дальше 1623703107.030645.png",
   "comments": [
      "Этот расказ интересен тока короткий больно охота проду : )",
      "Мне понравилось. Только я думала, что йоппы - это все-таки мы земляне.",
      "Очень понравилась книга.",
      "Не поцимаю, почему такая низкая оценка.",
      "Интересно. Много места для фантазии."
   ],
   "book_path": "library\\books\\А что с ними делать дальше 1623703107.030645.txt",
   "genres": [
      "Научная фантастика"
   ]
}