{
   "title": "Наложница императора",
   "author": "Семенова Татьяна",
   "img_path": "library\\images\\Наложница императора.png",
   "comments": [
      "Замечательная книга, в которой весьма интересно изложены исторические факты, вплетённые в роман о приключениях современных подростков))",
      "Книга очень увлекательная.",
      "Нужно прочитать не только подросткам, но и взрослым. Жаль, что вшколе нам этого не рассказывали."
   ],
   "book_path": "library\\books\\Наложница императора.txt",
   "genres": [
      "Детская образовательная литература",
      "Детская фантастика",
      "Научная фантастика"
   ],
   "timestamp": 1625592874.988978
}